bot_lens/Tracker.py
bot_lens/__init__.py
bot_lens-0.0.4.dist-info/LICENSE
bot_lens-0.0.4.dist-info/METADATA
bot_lens-0.0.4.dist-info/WHEEL
bot_lens-0.0.4.dist-info/top_level.txt
bot_lens-0.0.4.dist-info/RECORD
