Metadata-Version: 2.1
Name: bot-lens
Version: 0.0.4
Summary: API for tracking dat in ChatGPT plugins
Home-page: https://github.com/nicrso/bot-lens/
Author: bot_lens
Author-email: timtully24@gmail.com
Classifier: Programming Language :: Python :: 3
Classifier: License :: OSI Approved :: MIT License
Classifier: Operating System :: OS Independent
Requires-Python: >=3.7
License-File: LICENSE
